buffalo.libs/libgomp-a34b3233.so.1.0.0
buffalo-2.0.6.dist-info/NOTICE.md
buffalo-2.0.6.dist-info/WHEEL
buffalo-2.0.6.dist-info/METADATA
buffalo-2.0.6.dist-info/LICENSE
buffalo-2.0.6.dist-info/RECORD
buffalo-2.0.6.dist-info/top_level.txt
buffalo/__init__.py
buffalo/evaluate/base.py
buffalo/evaluate/__init__.py
buffalo/parallel/base.py
buffalo/parallel/__init__.py
buffalo/parallel/_core.cpython-38-x86_64-linux-gnu.so
buffalo/algo/_warp.cpython-38-x86_64-linux-gnu.so
buffalo/algo/_eals.cpython-38-x86_64-linux-gnu.so
buffalo/algo/_cfr.cpython-38-x86_64-linux-gnu.so
buffalo/algo/_bpr.cpython-38-x86_64-linux-gnu.so
buffalo/algo/_w2v.cpython-38-x86_64-linux-gnu.so
buffalo/algo/base.py
buffalo/algo/_plsi.cpython-38-x86_64-linux-gnu.so
buffalo/algo/__init__.py
buffalo/algo/_als.cpython-38-x86_64-linux-gnu.so
buffalo/algo/als.py
buffalo/algo/plsi.py
buffalo/algo/options.py
buffalo/algo/cfr.py
buffalo/algo/eals.py
buffalo/algo/warp.py
buffalo/algo/w2v.py
buffalo/algo/bpr.py
buffalo/data/mm.py
buffalo/data/base.py
buffalo/data/buffered_data.py
buffalo/data/stream.py
buffalo/data/__init__.py
buffalo/data/prepro.py
buffalo/data/fileio.cpython-38-x86_64-linux-gnu.so
buffalo/misc/__init__.py
buffalo/misc/util.py
buffalo/misc/_aux.py
buffalo/misc/log.py
buffalo/misc/_log.cpython-38-x86_64-linux-gnu.so
