Metadata-Version: 2.4
Name: buffalo
Version: 2.0.6
Summary: TOROS Buffalo: A fast and scalable production-ready open source project for recommender systems
Home-page: https://github.com/kakao/buffalo
Author: recoteam
Author-email: recoteam@kakaocorp.com
License: Apache2
Platform: Linux
Platform: MacOS
Classifier: Programming Language :: C++
Classifier: Programming Language :: Cython
Classifier: Programming Language :: Python
Classifier: Operating System :: POSIX :: Linux
Classifier: Operating System :: MacOS
Classifier: License :: OSI Approved :: Apache Software License
Requires-Python: >=3.8
License-File: LICENSE
License-File: NOTICE.md
Requires-Dist: numpy~=1.24.3
Requires-Dist: h5py~=3.9.0
Requires-Dist: psutil~=5.9.5
Requires-Dist: scipy~=1.10.1
Dynamic: license-file
